chdp/__init__.py
chdp/chdp_funcs.py
chdp/client.py
chdp/errors.py
chdp/handler.py
chdp-1.0.dist-info/LICENSE
chdp-1.0.dist-info/METADATA
chdp-1.0.dist-info/WHEEL
chdp-1.0.dist-info/top_level.txt
chdp-1.0.dist-info/RECORD
