Metadata-Version: 2.1
Name: chdp
Version: 1.0
Summary: Command Handler for Discord.Py
Home-page: https://github.com/kiki7000/chdp
Author: Tim232
Author-email: devkiki7000@gmail.com
License: GPL-V3
Keywords: discord,discord.py,commandhandler,chdp,handler,command
Platform: UNKNOWN
Requires-Python: >=3.8
Requires-Dist: discord.py
Requires-Dist: asyncio
Requires-Dist: importlib
